symmetrical_chainsaw/__init__.py
symmetrical_chainsaw/__main__.py
symmetrical_chainsaw/cli.py
symmetrical_chainsaw-0.0.17.dist-info/AUTHORS.rst
symmetrical_chainsaw-0.0.17.dist-info/LICENSE
symmetrical_chainsaw-0.0.17.dist-info/METADATA
symmetrical_chainsaw-0.0.17.dist-info/WHEEL
symmetrical_chainsaw-0.0.17.dist-info/top_level.txt
symmetrical_chainsaw-0.0.17.dist-info/RECORD
