Metadata-Version: 2.1
Name: symmetrical-chainsaw
Version: 0.0.17
Summary: test package
Home-page: https://github.com/yangchoo/symmetrical_chainsaw
Author: Yang
Author-email: me@yang.works
License: BSD-2-Clause
Project-URL: Documentation, https://symmetrical_chainsaw.readthedocs.io/
Project-URL: Changelog, https://symmetrical_chainsaw.readthedocs.io/en/latest/changelog.html
Project-URL: Issue Tracker, https://github.com/yangchoo/symmetrical_chainsaw/issues
Platform: UNKNOWN
Classifier: Intended Audience :: Developers
Classifier: License :: OSI Approved :: BSD License
Classifier: Operating System :: Unix
Classifier: Operating System :: POSIX
Classifier: Operating System :: Microsoft :: Windows
Classifier: Programming Language :: Python
Classifier: Programming Language :: Python :: 3
Classifier: Programming Language :: Python :: 3.5
Classifier: Programming Language :: Python :: 3.6
Classifier: Programming Language :: Python :: 3.7
Classifier: Programming Language :: Python :: 3.8
Classifier: Programming Language :: Python :: Implementation :: CPython
Classifier: Programming Language :: Python :: Implementation :: PyPy
Classifier: Topic :: Utilities
Requires-Python: >=3.5
